chksum_cli/__init__.py
chksum_cli/__main__.py
chksum_cli/chksum.py
chksum_cli/launcher.py
chksum_cli-1.1.0.dist-info/LICENSE
chksum_cli-1.1.0.dist-info/METADATA
chksum_cli-1.1.0.dist-info/WHEEL
chksum_cli-1.1.0.dist-info/entry_points.txt
chksum_cli-1.1.0.dist-info/top_level.txt
chksum_cli-1.1.0.dist-info/RECORD
