Metadata-Version: 2.1
Name: chksum-cli
Version: 1.1.0
Summary: Compare checksums from the command line
Author: espehon
Project-URL: Homepage, https://github.com/espehon/chksum-cli
Project-URL: Bug Tracker, https://github.com/espehon/chksum-cli/issues
Classifier: Programming Language :: Python :: 3
Classifier: Development Status :: 5 - Production/Stable
Classifier: Environment :: Console
Classifier: License :: OSI Approved :: GNU General Public License v3 (GPLv3)
Classifier: Operating System :: OS Independent
Classifier: Topic :: Utilities
Requires-Python: >=3.10
License-File: LICENSE
Requires-Dist: checksum (>=1.0.4)
Requires-Dist: colorama (>=0.4.6)
